{
  "TransitGateways": [],
  "ResponseMetadata": {
    "RequestId": "4a43e6b6-6adf-4350-ad60-ce1106e65540",
    "HTTPStatusCode": 200,
    "HTTPHeaders": {
      "x-amzn-requestid": "4a43e6b6-6adf-4350-ad60-ce1106e65540",
      "cache-control": "no-cache, no-store",
      "strict-transport-security": "max-age=31536000; includeSubDomains",
      "vary": "accept-encoding",
      "content-type": "text/xml;charset=UTF-8",
      "transfer-encoding": "chunked",
      "date": "Tue, 03 Jun 2025 14:43:09 GMT",
      "server": "AmazonEC2"
    },
    "RetryAttempts": 0
  }
}