{
  "Compliance Name": "aws_foundational_security_best_practices_aws",
  "ID": "ELB.3",
  "Name": "Classic Load Balancer listeners should be configured with HTTPS or TLS termination",
  "Description": "This control checks whether your Classic Load Balancer listeners are configured with HTTPS or TLS protocol for front-end (client to load balancer) connections.",
  "Function Name": "elbv2_internet_facing",
  "clients": ["elbv2"],
  "functions": {
    "elbv2": {
      "method": "describe_load_balancers",
      "field_path": "LoadBalancers[].Scheme"
    }
  },
  "evaluation": {
    "type": "not_exists",
    "source_client": "elbv2",
    "field": "Scheme",
    "value": "internet-facing"
  }
}
