{
  "ResponseMetadata": {
    "RequestId": "7f76cc77-4c6c-452a-be90-e4fda39248b0",
    "HTTPStatusCode": 200,
    "HTTPHeaders": {
      "x-amzn-requestid": "7f76cc77-4c6c-452a-be90-e4fda39248b0",
      "content-type": "text/xml",
      "content-length": "276",
      "date": "Tue, 03 Jun 2025 14:55:58 GMT"
    },
    "RetryAttempts": 0
  },
  "Tags": {
    "Items": [
      {
        "Key": "Environment",
        "Value": "prod"
      },
      {
        "Key": "Name",
        "Value": "noproject-prod-lgtech.in"
      },
      {
        "Key": "Project",
        "Value": "noproject"
      }
    ]
  }
}